agorae/__init__.py
agorae/__version__.py
agorae-0.1.0.dev0.dist-info/LICENSE
agorae-0.1.0.dev0.dist-info/METADATA
agorae-0.1.0.dev0.dist-info/WHEEL
agorae-0.1.0.dev0.dist-info/top_level.txt
agorae-0.1.0.dev0.dist-info/RECORD
