Metadata-Version: 2.1
Name: agorae
Version: 0.1.0.dev0
Summary: agorae
Home-page: UNKNOWN
Author: Sylvain Bellemare
Author-email: sbellem@gmail.com
License: UNKNOWN
Platform: UNKNOWN
Classifier: Development Status :: 1 - Planning
Classifier: Programming Language :: Python
Classifier: Programming Language :: Python :: 3
Classifier: Programming Language :: Python :: 3.7
Classifier: Programming Language :: Python :: Implementation :: CPython
Requires-Python: >=3.7.0
